Metadata-Version: 2.1
Name: sepbit.sistamapy
Version: 1.0.0
Summary: Simple statuses Mastodon for Python
Home-page: https://gitlab.com/sepbit/sistamapy
Author: Vitor Guia
Author-email: contato@vitor.guia.nom.br
Maintainer: Sepbit
Maintainer-email: contato@sepbit.com
License: GPL-3.0-or-later
Keywords: Statuses Mastodon Python
Platform: UNKNOWN
Classifier: Development Status :: 5 - Production/Stable
Classifier: Intended Audience :: Developers
Classifier: License :: OSI Approved :: GNU General Public License v3 or later (GPLv3+)
Classifier: Programming Language :: Python :: 3.9
Classifier: Programming Language :: Python :: Implementation :: CPython
Classifier: Programming Language :: Python :: Implementation :: PyPy
Requires-Python: ~=3.9
Provides-Extra: dev
Provides-Extra: test
License-File: COPYING
